README.md
setup.py
LocalJudge.egg-info/PKG-INFO
LocalJudge.egg-info/SOURCES.txt
LocalJudge.egg-info/dependency_links.txt
LocalJudge.egg-info/entry_points.txt
LocalJudge.egg-info/not-zip-safe
LocalJudge.egg-info/requires.txt
LocalJudge.egg-info/top_level.txt
lj/__init__.py
lj/lj.py
lj/ljc.py
lj/utils.py
test/test.py