Metadata-Version: 2.1
Name: LocalJudge
Version: 0.0.1
Summary: LocalJudge
Home-page: https://github.com/NoCLin/LocalJudge
Author: NoCLin
Author-email: engineelin@gmail.com
License: MIT Licence
Platform: UNKNOWN
Classifier: Programming Language :: Python :: 3
Classifier: License :: OSI Approved :: MIT License
Classifier: Operating System :: OS Independent
